{"stats":{"minecraft:used":{"minecraft:chain":14,"vanilla_plus:red_lantern":1,"vanilla_plus:green_lantern":1,"vanilla_plus:yellow_lantern":1},"minecraft:custom":{"minecraft:jump":4,"minecraft:time_since_rest":3332,"minecraft:crouch_one_cm":327,"minecraft:leave_game":1,"minecraft:play_time":3332,"minecraft:time_since_death":3332,"minecraft:walk_one_cm":2568,"minecraft:sneak_time":264,"minecraft:total_world_time":3434,"minecraft:interact_with_crafting_table":1,"minecraft:fly_one_cm":1720}},"DataVersion":2865}